{"keys": ["", "1748", "1724", "1742"], "data": {"1724": {"CENA": 36.9, "JMENO": "Jarom\u00edr Krch\u0148av\u00fd", "AKTUALIZAC": "04.11.2014 12:31", "NAZEV": "Jarom\u00edr Krch\u0148av\u00fd, Host\u011bradice"}, "1748": {"CENA": 36.9, "JMENO": "A+S", "AKTUALIZAC": "04.11.2014 12:24", "NAZEV": "A+S, Znojemsk\u00e1, Moravsk\u00fd Krumlov"}, "1742": {"CENA": 36.9, "JMENO": "Benaz", "AKTUALIZAC": "04.11.2014 12:26", "NAZEV": "Benaz, N\u00e1dra\u017en\u00ed 1178, Miroslav"}}, "grid": ["                                                 !!             ", "                                                                ", "                                                                ", "                                                                ", "                                                                ", "                                                                ", "                                                                ", "                                                                ", "                                                                ", "                                                                ", "                                                                ", "                                                                ", "                                                                ", "                                                                ", "                                                                ", "                                                                ", "                                                                ", "                                                                ", "                                                                ", "                                                                ", "                                                                ", "                                                                ", "                                                                ", "                                                                ", "                                                                ", "                                                                ", "                                                                ", "                                                                ", "                                                                ", "                                                                ", "                                                                ", "                                                                ", "                                                                ", "                                                                ", "                                                                ", "                                                                ", "                                                                ", "                                                                ", "                                                                ", "                                                                ", "                                                                ", "                                                                ", "                                                                ", "                                                                ", "                                                                ", "                                                                ", "                                                                ", "                                                                ", "                                                                ", "                             #                                  ", "                            ##                                  ", "                                                                ", "                                                                ", "                                                                ", "                                                       $$       ", "                                                       $$       ", "                                                                ", "                                                                ", "                                                                ", "                                                                ", "                                                                ", "                                                                ", "                                                                ", "                                                                "]}