{"keys": ["", "1126", "655"], "data": {"655": {"CENA": 34.9, "JMENO": "EuroOil", "AKTUALIZAC": "05.11.2014 05:02", "NAZEV": "EuroOil, silnice 21, Plze\u0148sk\u00e1 855, Plan\u00e1"}, "1126": {"CENA": 36.2, "JMENO": "OMV", "AKTUALIZAC": "04.11.2014 16:22", "NAZEV": "OMV, Plze\u0148sk\u00e1, Mari\u00e1nsk\u00e9 L\u00e1zn\u011b"}}, "grid": ["                 !                                              ", "                                                                ", "                                                                ", "                                                                ", "                                                                ", "                                                                ", "                                                                ", "                                                                ", "                                                                ", "                                                                ", "                                                                ", "                                                                ", "                                                                ", "                                                                ", "                                                                ", "                                                                ", "                                                                ", "                                                                ", "                                                                ", "                                                                ", "                                                                ", "                                                                ", "                                                                ", "                                                                ", "                                                                ", "                                                                ", "                                                                ", "                                                                ", "                                                                ", "                                                                ", "                                                                ", "                                                                ", "                                                                ", "                                                                ", "                                                                ", "                                                                ", "                                                                ", "                                                                ", "                                                                ", "                                                                ", "                                                                ", "                                                                ", "                                                                ", "                                                                ", "                                                                ", "                                                                ", "                                                                ", "                                                                ", "                                                                ", "                             #                                  ", "                             ##                                 ", "                                                                ", "                                                                ", "                                                                ", "                                                                ", "                                                                ", "                                                                ", "                                                                ", "                                                                ", "                                                                ", "                                                                ", "                                                                ", "                                                                ", "                                                                "]}