{"keys": ["", "12", "1500", "1501", "1507", "596", "1350"], "data": {"12": {"CENA": 33.1, "JMENO": "Auto Peli", "AKTUALIZAC": "05.11.2014 10:34", "NAZEV": "Auto Peli, P\u00edsek, Vrcovick\u00e1 2230"}, "596": {"CENA": 35.2, "JMENO": "EuroOil", "AKTUALIZAC": "05.11.2014 05:02", "NAZEV": "EuroOil, U H\u0159eb\u010dince 2581/17, P\u00edsek"}, "1350": {"CENA": 36.4, "JMENO": "OMV", "AKTUALIZAC": "04.11.2014 15:06", "NAZEV": "OMV, U H\u0159eb\u010dince, P\u00edsek"}, "1500": {"CENA": 34.9, "JMENO": "OMV", "AKTUALIZAC": "04.11.2014 14:12", "NAZEV": "OMV, T\u00e1borsk\u00e1 2470/16, P\u00edsek"}, "1501": {"CENA": 35.6, "JMENO": "RoBiN OIL", "AKTUALIZAC": "04.11.2014 14:12", "NAZEV": "RoBiN OIL, s.r.o., T\u00e1borsk\u00e1 2260, P\u00edsek"}, "1507": {"CENA": 34.9, "JMENO": "Karel Frol\u00edk", "AKTUALIZAC": "04.11.2014 14:11", "NAZEV": "Karel Frol\u00edk, T\u00e1borsk\u00e1 2400/10, P\u00edsek"}}, "grid": ["                                                                ", "                                                                ", "                                                                ", "                                                                ", "                                                                ", "                                                                ", "                                                                ", "                                                                ", "                                                                ", "                                                                ", "                                                                ", "                                                                ", "                                                                ", "                                                                ", "                                                                ", "                                                                ", "          !!                                                    ", "          !!                                                    ", "                                                                ", "                                                                ", "                                                                ", "                   #$                                           ", "                   #$                                           ", "                  %%                                            ", "                  %                                             ", "                                                                ", "                                                                ", "                                                                ", "                                                                ", "                                                                ", "                                                                ", "                                                                ", "                                                                ", "                                                                ", "                                                                ", "                                                                ", "                                                                ", "                                                                ", "                                                                ", "                                                                ", "                                                                ", "                                                                ", "                                                                ", "                                                                ", "                                                                ", "                                                                ", "                                                                ", "                                                                ", "                                                                ", "                                                                ", "                                                                ", "                                                                ", "                                                                ", "                                                                ", "                                                                ", "                                                                ", "                                                                ", "                                                                ", "                                                                ", "                                                                ", "                   &&                                           ", "                   &&                                           ", "               ''                                               ", "               ''                                               "]}