{"keys": ["", "1356", "1366", "159", "1362", "155", "31"], "data": {"155": {"CENA": 39.9, "JMENO": "Agip", "AKTUALIZAC": "05.11.2014 09:42", "NAZEV": "Agip, d\u00e1lnice D1, sm\u011br Praha, Her\u00e1lec-Mikul\u00e1\u0161ov"}, "159": {"CENA": 39.9, "JMENO": "Shell Czech Republic", "AKTUALIZAC": "05.11.2014 09:42", "NAZEV": "Shell Czech Republic, a.s., d\u00e1lnice D1, sm\u011br Praha"}, "31": {"CENA": 39.9, "JMENO": "OMV", "AKTUALIZAC": "05.11.2014 10:24", "NAZEV": "OMV, d\u00e1lnice D1, sm\u011br Brno, Her\u00e1lec-Mikul\u00e1\u0161ov"}, "1356": {"CENA": 34.5, "JMENO": "ICOM Transport", "AKTUALIZAC": "04.11.2014 15:04", "NAZEV": "ICOM Transport, Okru\u017en\u00ed 612, Humpolec"}, "1366": {"CENA": 34.9, "JMENO": "Benzina", "AKTUALIZAC": "04.11.2014 15:01", "NAZEV": "Benzina, 5.kv\u011btna 1540, Humpolec"}, "1362": {"CENA": 35.4, "JMENO": "Benzina Plus", "AKTUALIZAC": "04.11.2014 15:02", "NAZEV": "Benzina Plus, silnice 34, Vystrkov"}}, "grid": ["                                                                ", "                                                                ", "                                                                ", "                                                                ", "                                                                ", "                                                                ", "                                                                ", "                                                                ", "                                                                ", "                                                                ", "                                                                ", "                                                                ", "                                                                ", "                                                                ", "                                                                ", "                                                                ", "                                                                ", "                                                                ", "                                                                ", "                                                                ", "                                                                ", "                                                                ", "                                                                ", "                                                                ", "                                                                ", "                                                                ", "                                                                ", "                                                                ", "                                                                ", "                                                                ", "                                                                ", "                                                                ", "                                                                ", "                                                                ", "                                                                ", "                                                                ", "                                                                ", "                                                                ", "                                                                ", "                  !!                                            ", "                  !!       #                                    ", "              $$           #                                    ", "              $$                                                ", "                                                                ", "                                                                ", "                                                                ", "                                                                ", "                                                                ", "                                                                ", "                   %%                                           ", "                   %%                                           ", "                                                                ", "                                                                ", "                                            &&                  ", "                                            &&'                 ", "                                                                ", "                                                                ", "                                                                ", "                                                                ", "                                                                ", "                                                                ", "                                                                ", "                                                                ", "                                                                "]}