{"keys": ["", "1437", "1436"], "data": {"1436": {"CENA": 35.7, "JMENO": "T.V.G.", "AKTUALIZAC": "04.11.2014 14:46", "NAZEV": "T.V.G., Brn\u011bnsk\u00e1, Holasice"}, "1437": {"CENA": 35.9, "JMENO": "TOP Petrol", "AKTUALIZAC": "04.11.2014 14:46", "NAZEV": "TOP Petrol, Masarykova, Rajhrad"}}, "grid": ["                                                        !!      ", "                                                                ", "                                                                ", "                                                                ", "                                                                ", "                                                                ", "                                                                ", "                                                                ", "                                                                ", "                                                                ", "                                                                ", "                                                                ", "                                                                ", "                                                                ", "                                                                ", "                                                                ", "                                                                ", "                                                                ", "                                                           #    ", "                                                          ##    ", "                                                                ", "                                                                ", "                                                                ", "                                                                ", "                                                                ", "                                                                ", "                                                                ", "                                                                ", "                                                                ", "                                                                ", "                                                                ", "                                                                ", "                                                                ", "                                                                ", "                                                                ", "                                                                ", "                                                                ", "                                                                ", "                                                                ", "                                                                ", "                                                                ", "                                                                ", "                                                                ", "                                                                ", "                                                                ", "                                                                ", "                                                                ", "                                                                ", "                                                                ", "                                                                ", "                                                                ", "                                                                ", "                                                                ", "                                                                ", "                                                                ", "                                                                ", "                                                                ", "                                                                ", "                                                                ", "                                                                ", "                                                                ", "                                                                ", "                                                                ", "                                                                "]}